SurvivalEVAL/Evaluator.py
SurvivalEVAL/IntervalCenEvaluator.py
SurvivalEVAL/__init__.py
SurvivalEVAL/version.py
SurvivalEVAL/Evaluations/AreaUnderPRCurve.py
SurvivalEVAL/Evaluations/AreaUnderROCurve.py
SurvivalEVAL/Evaluations/BrierScore.py
SurvivalEVAL/Evaluations/Concordance.py
SurvivalEVAL/Evaluations/DistributionCalibration.py
SurvivalEVAL/Evaluations/MeanError.py
SurvivalEVAL/Evaluations/OtherMetrics.py
SurvivalEVAL/Evaluations/SingleTimeCalibration.py
SurvivalEVAL/Evaluations/__init__.py
SurvivalEVAL/Evaluations/custom_types.py
SurvivalEVAL/Evaluations/util.py
SurvivalEVAL/Evaluations/util_plots.py
SurvivalEVAL/NonparametricEstimator/CompetingRisks.py
SurvivalEVAL/NonparametricEstimator/SingleEvent.py
SurvivalEVAL/NonparametricEstimator/__init__.py
examples/plots_for_survey/all_metrics_illustration.py
examples/plots_for_survey/best_guess_times.py
examples/plots_for_survey/disc_vs_calib.py
examples/plots_for_survey/distribution_calibration.py
examples/plots_for_survey/km_calibration.py
examples/plots_for_survey/log_rank.py
examples/plots_for_survey/motivation_of_distribution_calibration.py
examples/plots_for_survey/residuals.py
examples/plots_for_survey/single_time_calibration.py
examples/plots_for_survey/types_of_outcomes.py
survivaleval-0.6.0.dist-info/licenses/LICENSE
tests/IntervalCensorDGP.py
tests/test_IntervalCensorDGP.py
tests/test_evaluator.py
tests/test_ibs.py
tests/test_ici.py
tests/test_interval_cen_evaluator.py
tests/test_lifelines.py
tests/test_multiple_brier.py
tests/test_point_evaluator.py
tests/test_pycox.py
tests/test_quantile_evaluator.py
tests/test_right2interval.py
tests/test_single_event.py
tests/private/integrated_calibration_index.py
tests/private/test.py
tests/private/test_fast_PO.py
tests/private/test_ic_concordance.py
tests/private/test_kmcal.py
tests/private/test_po.py
tests/private/test_predict_st.py
survivaleval-0.6.0.dist-info/METADATA
survivaleval-0.6.0.dist-info/WHEEL
survivaleval-0.6.0.dist-info/top_level.txt
survivaleval-0.6.0.dist-info/RECORD
