Metadata-Version: 2.4
Name: SurvivalEVAL
Version: 0.6.0
Summary: The most comprehensive Python package for evaluating survival analysis models.
Home-page: https://github.com/shi-ang/SurvivalEVAL
Author: Shi-ang Qi, Weijie Sun
Author-email: Shi-ang Qi <shiang@ualberta.ca>, Weijie Sun <weijie2@ualberta.ca>
License:                     GNU GENERAL PUBLIC LICENSE
Project-URL: Homepage, https://github.com/shi-ang/SurvivalEVAL
Project-URL: Documentation, https://github.com/shi-ang/SurvivalEVAL/blob/main/README.md
Project-URL: Issues, https://github.com/shi-ang/SurvivalEVAL/issues
Project-URL: Changelog, https://github.com/shi-ang/SurvivalEVAL/blob/main/CHANGELOG.md
Classifier: Programming Language :: Python :: 3
Classifier: License :: OSI Approved :: GNU General Public License v3 (GPLv3)
Classifier: Topic :: Scientific/Engineering
Classifier: Programming Language :: Python
Classifier: Programming Language :: Python :: 3.9
Classifier: Programming Language :: Python :: 3.10
Classifier: Programming Language :: Python :: 3.11
Classifier: Programming Language :: Python :: 3.12
Classifier: Programming Language :: Python :: 3.13
Classifier: Operating System :: OS Independent
Classifier: Intended Audience :: Science/Research
Classifier: Intended Audience :: Developers
Classifier: Topic :: Software Development :: Libraries
Classifier: Topic :: Scientific/Engineering :: Information Analysis
Classifier: Topic :: Scientific/Engineering :: Mathematics
Classifier: Topic :: Scientific/Engineering :: Artificial Intelligence
Requires-Python: >=3.9
License-File: LICENSE
Requires-Dist: torch>=1.0.0
Requires-Dist: numpy>=1.26.0
Requires-Dist: pandas>=2.0.3
Requires-Dist: tqdm>=4.49.0
Requires-Dist: scipy>=1.11.1
Requires-Dist: matplotlib>=3.4.3
Requires-Dist: scikit-learn>=1.5.2
Requires-Dist: lifelines>=0.30.0
Requires-Dist: patsy>=1.0.1
Provides-Extra: dev
Requires-Dist: pycox>=0.2.3; extra == "dev"
Requires-Dist: scikit-survival>=0.20.2; extra == "dev"
Requires-Dist: pytest>=7.4.0; extra == "dev"
Dynamic: author
Dynamic: home-page
Dynamic: license-file
Dynamic: requires-python
